testcontainers/rabbitmq/__init__.py
tests/test_rabbitmq.py
testcontainers_rabbitmq-0.0.1rc1.dist-info/METADATA
testcontainers_rabbitmq-0.0.1rc1.dist-info/WHEEL
testcontainers_rabbitmq-0.0.1rc1.dist-info/top_level.txt
testcontainers_rabbitmq-0.0.1rc1.dist-info/RECORD
